{
	"info": {
		"_postman_id": "fa82bf9d-d29d-4fff-9db1-ddbc4c47d9c6",
		"name": "API_1",
		"schema": "https://schema.getpostman.com/json/collection/v2.1.0/collection.json"
	},
	"item": [
		{
			"name": "GET : todas las pelis",
			"request": {
				"method": "GET",
				"header": [],
				"url": {
					"raw": "http://localhost:4000/api/movies/",
					"protocol": "http",
					"host": [
						"localhost"
					],
					"port": "4000",
					"path": [
						"api",
						"movies",
						""
					]
				}
			},
			"response": []
		},
		{
			"name": "POST: agregar pelicula",
			"request": {
				"method": "POST",
				"header": [],
				"body": {
					"mode": "raw",
					"raw": "{\r\n     \"title\":\"MIGUESAURUS\", \r\n     \"director\": \"JS DIRECTOR\", \r\n     \"year\": \"2022\", \r\n     \"rating\": \"1234\" \r\n}",
					"options": {
						"raw": {
							"language": "json"
						}
					}
				},
				"url": {
					"raw": "http://localhost:4000/api/movies",
					"protocol": "http",
					"host": [
						"localhost"
					],
					"port": "4000",
					"path": [
						"api",
						"movies"
					]
				}
			},
			"response": []
		},
		{
			"name": "PUT: actualizando pelicula",
			"request": {
				"method": "PUT",
				"header": [],
				"body": {
					"mode": "raw",
					"raw": "{\r\n     \"title\":\"jurasic park\", \r\n     \"director\": \"JS DIRECTOR\", \r\n     \"year\": \"2022\", \r\n     \"rating\": \"1234\" \r\n}",
					"options": {
						"raw": {
							"language": "json"
						}
					}
				},
				"url": {
					"raw": "http://localhost:4000/api/movies/5",
					"protocol": "http",
					"host": [
						"localhost"
					],
					"port": "4000",
					"path": [
						"api",
						"movies",
						"5"
					]
				}
			},
			"response": []
		},
		{
			"name": "DELETE: eliminar pelicula",
			"request": {
				"method": "DELETE",
				"header": [
					{
						"key": "Content-Type",
						"value": "text/plain",
						"type": "text"
					},
					{
						"key": "Content-Type",
						"value": "",
						"type": "text"
					},
					{
						"key": "Content-Type",
						"value": "",
						"type": "text"
					},
					{
						"key": "Content-Type",
						"value": "application/json",
						"type": "text"
					}
				],
				"body": {
					"mode": "raw",
					"raw": "",
					"options": {
						"raw": {
							"language": "json"
						}
					}
				},
				"url": {
					"raw": "http://localhost:4000/api/movies/3",
					"protocol": "http",
					"host": [
						"localhost"
					],
					"port": "4000",
					"path": [
						"api",
						"movies",
						"3"
					]
				}
			},
			"response": []
		}
	]
}